{
  "013f655005": "Bill Nummer",
  "03cae7f5ea": "Bestel Totaal",
  "071b975857": "Herberekenen",
  "096b73624b": "Besparing",
  "09bf25ef30": "E-mail adres",
  "0a4e0b71b7": "Bijwerken ...",
  "0f725e8596": "Orde werd betaald na factuur verstreken.",
  "0fd0d74a1f": "Geldig voor:",
  "10bb8c465d": "Opnieuw verzenden IPN",
  "1448c140a4": "Adres (vervolg)",
  "1455c41ad9": "Niet opgeslagen",
  "1668dd2051": "BitPay, de gemakkelijke manier om te betalen met Bitcoins.",
  "181e5d8629": "Android Apps",
  "183f00f483": "Houden",
  "1944cd04bc": "Factuur Verlopen",
  "1a9e117e2b": "Kopers moeten niet een aankoop als je reden hebt om te vermoeden dat het een scam of het is een bedrag dat u niet bereid bent te verliezen in het geval dat het is.",
  "1d0a4159fc": "Aanpassen App",
  "2215489ead": "Apple Apps",
  "252720a678": "Bij uw aankoop: Informatie",
  "268ad70eb5": "betaald",
  "2ae711c6cd": "De wereldleider in Bitcoin Payment Processing",
  "2b5c3d2672": "Contact",
  "2ccc42c074": "Pakbon",
  "2dd10c5498": "Een terugbetaling is de verwerking van deze bestelling.",
  "31b4862905": "De Klik om bitcoin URI Betaal wordt ondersteund door Multibit, Armory, Blockchain App (Apple en Android), BitcoinSpinner App (Android), en Bitcoin Wallet (Android)",
  "34fcd078d7": "Transfer naar telefoon",
  "35322b5bb5": "Wijzigingen opslaan",
  "370e9d2bbc": "Terug wijzigen",
  "3a5ecca188": "Updated",
  "3ac1a9ec4f": "Valuta",
  "3bce0619e4": "BitPay verwerkt betalingen in naam van handelaren maar we weten niet bemiddelen geschillen.",
  "3d49022980": "De klant betaalde deze bestelling.",
  "3d87409b46": "Powered by BitPay.com",
  "3e6105cdba": "Taalinstelling",
  "4085118690": "portefeuilles",
  "41150bed3b": "Bestel wordt gedeeltelijk betaald en factuur is verstreken.",
  "43e648ac03": "Display Taal:",
  "4499f11dfc": "U heeft teveel betaald deze bestelling.",
  "458a4770df": "verschuldigd",
  "47e2886ee5": "Belasting",
  "492308d641": "Uw bestelling is gedeeltelijk betaald en de factuur is verstreken. Stuur geen betalingen meer naar dit adres.",
  "49e96d7cdf": "Bedrag",
  "4c94ba8d65": "Factuur is geldig voor:",
  "53287e6aae": "Vul Bestel",
  "54a0e8c17e": "Fout",
  "56ef8f2095": "Adres",
  "57870fd030": "Vervaldag",
  "5be28ea2f9": "SUBTOTAAL",
  "5cf9e7527f": "Bestelinformatie",
  "652bcc3a47": "Item",
  "68767446ea": "Item List",
  "6b37bd3508": "Terugbetalen",
  "6d2d59aed4": "Kar",
  "6e24470fce": "Verzendadres",
  "701d021d08": "Land",
  "70315b5027": "Ontvangst Details",
  "7048f38b33": "Betaling",
  "72dba9aeed": "Telefoonnummer",
  "72de93501c": "Factuur Help",
  "7a552636e3": "OPMERKING",
  "7b0c9bb304": "E-mail ontvangst",
  "7d9eb7acb1": "Sluiten",
  "809753fdaa": "Inschrijving Detail",
  "809f9470d2": "Merchants Alleen",
  "822bab8d41": "Hoeveelheid",
  "89713b9c9c": "Aanvaarden",
  "899acf9f40": "Staat / Provincie",
  "8caaef4c05": "Doorgaan naar",
  "8d368efb8e": "Geen items in uw winkelwagen.",
  "8d8cd546b5": "Meer info",
  "9222bf3152": "Bestelnummer",
  "93c91c851e": "Prijs",
  "98bad4f12c": "Print Ontvangst",
  "99e71f48c4": "Uitchecken",
  "9bd88f2485": "Desktop",
  "a00a79ef36": "Get Bitcoins",
  "a12ef86976": "Bill Info",
  "a9715d5277": "Al ingevuld",
  "ab2882c864": "TOTAAL",
  "ab604a3607": "Verwerpen",
  "ad5751430e": "Scheepvaart",
  "aef6d947e2": "Item Prijzen zijn onderhevig aan verandering totdat u afrekenen.",
  "b10bb38741": "Vraag een teruggave",
  "b171c8a14b": "Opgeslagen BitPay winkelwagen",
  "b40b12d2c9": "Bitcoins aan te pakken:",
  "b5c120b316": "Opgeslagen",
  "b79cac926e": "Help",
  "b832002da2": "Factuur",
  "bc40dd05da": "Deze portefeuilles ondersteunen",
  "bf5af97c64": "ZIP / Postal Code",
  "bf9bc4ddf0": "Bitcoin Adres niet beschikbaar",
  "c401c8b19b": "Teveel betaalde bedrag",
  "c41bfa5f0b": "URI compatibel",
  "c65a4c7e21": "Text to Pay",
  "cdf7689a4e": "Customer Service",
  "d00aae6b7f": "Winkel",
  "d011908f0d": "Klik om te betalen",
  "d4bff4f8ff": "Bitcoin Sale",
  "d6dfce74a1": "BitPay Ontvangst",
  "d7b5a725ac": "Bestelling is betaald.",
  "d9f3d71301": "Bitcoins naar:",
  "dad5a96923": "Ontvangst",
  "db2bafedda": "Deze factuur is verlopen. Een verzoek tot teruggave.",
  "dbe733d533": "BitPay doet ons best om te screenen op eerlijke handelaars, en we zullen eindigen relaties als we een handelaar te zijn oneerlijk.",
  "dcd1d5223f": "Naam",
  "dea4b6e0b1": "Stuur Bitcoins:",
  "df0fe79898": "Afdrukken",
  "e162ef63fc": "Compatibel Portemonnees",
  "e2bf318da3": "Deze factuur is verlopen. Stuur geen betaling.",
  "e2d0a54968": "Verwijder",
  "e371864bce": "Wilt u dit item uit uw winkelwagen?",
  "e51783b4d7": "Bill",
  "e9143587eb": "Betalingsgegevens",
  "e96d0b55f3": "Keer terug naar",
  "ebfb49e7f2": "Uitsluitend met",
  "ec549131f4": "Aan te pakken:",
  "ecb075f982": "Herberekenen",
  "ed9cb8655e": "Scannen naar Pay",
  "f1f295aa4b": "Probleem Refund",
  "f6f4688ff2": "Sturen",
  "f8d47b82e2": "Contact opnemen met ondersteuning",
  "fa8ed0bdab": "Plan",
  "fc33f73246": "City",
  "fc6d420adb": "Uw factuur is verlopen. Stuur geen betalingen meer naar dit adres.",
  "fce8c7f428": "Volgende betaling is verschuldigd",
  "fcfc382915": "Item verwijderen",
  "ff11d43060": "Betaal deze factuur"
}